{
  "hello": "*Hi there! How can I help you ❔*\n\n> *ᴘᴏᴡᴇʀ ʙʏ ʀᴇᴀʟ ᴅᴇxᴛᴇʀ*",
  "hi": "*Hi there! How can I help you ❔*\n\n> *ᴘᴏᴡᴇʀ ʙʏ ʀᴇᴀʟ ᴅᴇxᴛᴇʀ*",
  "dexter": "*YES IAM REAL DEXTER PROGRAMMER 👋*",
  "ʙᴜʏ-ʙʀᴏᴀᴅᴄᴀꜱᴛ-ɪᴅ": "*BROADCAST SITE CREATE OWNER NAME* 🔔\n\n*එ කිය්න්නෙ Broadcast site එක අපි දෙනවා ඔයගෙ නමටම හදලා සති 2 ක් යනකම් වග කියනවා එ site එක අපෙන් ඔය පොඩි ගනකට Buy කරලා ඉට වඩා හම්බ කරන kollo ඉන්නවා එ නිසා මෙය හොද Business එකක්* \n\n*PRICE එක ඇවිත් අද OFFER එකක් නිසා Rs.500 ක් පමණයි* ‼️",
  "me": "*ඔ කියන්න* 😒 ❔",
  "gm": "*GOOD MORNING 🌼*",
  "Mk": "*මුකුත් නැ ඔයා මොකක්ද කරන්නෙ ❔*",
  "contact-push": "*CONTACT PUSH V2 UPDATE SUCCESS* ‼️\n\n*CONTACT PUSH V2 PROFESSIONAL BUSINESS TOOL* 🔔\n\n> *BUY CONTACT PUSH V2* 🕊️"
}